setup.py
python_prefork/__init__.py
python_prefork/python_prefork.py
python_prefork/python_prefork_test.py
python_prefork.egg-info/PKG-INFO
python_prefork.egg-info/SOURCES.txt
python_prefork.egg-info/dependency_links.txt
python_prefork.egg-info/top_level.txt