Metadata-Version: 1.0
Name: python-prefork
Version: 0.1.2
Summary: parallel processing fork manager inspired by Parallel::Prefork in CPAN
Home-page: http://github.com/taichino/python_prefork
Author: Matsumoto Taichi (taichino@gmail.com)
Author-email: taichino@gmail.com
License: MIT License
Keywords: multi process,parallel,prefork
Platform: UNKNOWN
Classifier: Development Status :: 3 - Alpha
Classifier: Intended Audience :: Developers
Classifier: License :: OSI Approved :: MIT License
Classifier: Operating System :: POSIX
Classifier: Programming Language :: Python
Classifier: Topic :: Software Development :: Libraries :: Python Modules
